eccw_gui/__init__.py
eccw_gui/__main__.py
eccw_gui/calculator_app/__init__.py
eccw_gui/calculator_app/controllers/__init__.py
eccw_gui/calculator_app/controllers/calculator_main.py
eccw_gui/calculator_app/viewers/__init__.py
eccw_gui/calculator_app/viewers/calculator_main.py
eccw_gui/documentation/ECCW.epub
eccw_gui/documentation/ECCW.pdf
eccw_gui/documentation/__init__.py
eccw_gui/images/__init__.py
eccw_gui/images/ressources_rc.py
eccw_gui/main_app/__init__.py
eccw_gui/main_app/controllers/__init__.py
eccw_gui/main_app/controllers/dialog_about.py
eccw_gui/main_app/controllers/main.py
eccw_gui/main_app/viewers/__init__.py
eccw_gui/main_app/viewers/dialog_about.py
eccw_gui/main_app/viewers/main.py
eccw_gui/plot_app/__init__.py
eccw_gui/plot_app/controllers/__init__.py
eccw_gui/plot_app/controllers/curve_graphicSettings.py
eccw_gui/plot_app/controllers/curve_settings.py
eccw_gui/plot_app/controllers/dialog_errors.py
eccw_gui/plot_app/controllers/plot_main.py
eccw_gui/plot_app/controllers/plot_window.py
eccw_gui/plot_app/controllers/point_settings.py
eccw_gui/plot_app/controllers/title_settings.py
eccw_gui/plot_app/viewers/__init__.py
eccw_gui/plot_app/viewers/curve_graphicSettings.py
eccw_gui/plot_app/viewers/curve_settings.py
eccw_gui/plot_app/viewers/dialog_errors.py
eccw_gui/plot_app/viewers/plot_main.py
eccw_gui/plot_app/viewers/plot_window.py
eccw_gui/plot_app/viewers/point_settings.py
eccw_gui/plot_app/viewers/title_settings.py
eccw_gui/shared/__init__.py
eccw_gui/shared/file_management.py
eccw_gui/shared/tools.py
eccw_gui/shared/wrappers.py
eccw_gui/shared/controllers/__init__.py
eccw_gui/shared/controllers/checkBox.py
eccw_gui/shared/controllers/colorButton.py
eccw_gui/shared/controllers/comboBox.py
eccw_gui/shared/controllers/groupBox.py
eccw_gui/shared/controllers/label.py
eccw_gui/shared/controllers/layout.py
eccw_gui/shared/controllers/lineEdit.py
eccw_gui/shared/controllers/radioButton.py
eccw_gui/shared/controllers/spinBox.py
eccw_gui-1.1.4.dist-info/AUTHORS.md
eccw_gui-1.1.4.dist-info/LICENCE.txt
eccw_gui-1.1.4.dist-info/METADATA
eccw_gui-1.1.4.dist-info/WHEEL
eccw_gui-1.1.4.dist-info/entry_points.txt
eccw_gui-1.1.4.dist-info/top_level.txt
eccw_gui-1.1.4.dist-info/RECORD
