Metadata-Version: 2.1
Name: eccw-gui
Version: 1.1.4
Summary: Exact Critical Coulomb Wedge - Graphical User Interface: tools to compute and display the exact solution of any parameter of Critical Coulomb Wedge
Home-page: https://github.com/bclmary/eccw_gui
Author: BCL Mary, YM Leroy, Xiaoping Yuan, Pauline Souloumiac, Chong Wu
Author-email: baptiste.mary@cyu.fr
Maintainer: BCL Mary
Maintainer-email: baptiste.mary@u-cergy.fr
License: GPL-3.0+
Keywords: geology,accretionnary prism,science,PyQt5
Platform: any
Classifier: Development Status :: 5 - Production/Stable
Classifier: License :: OSI Approved :: GNU General Public License v3 or later (GPLv3+)
Classifier: Natural Language :: English
Classifier: Environment :: X11 Applications :: Qt
Classifier: Environment :: Console
Classifier: Programming Language :: Python :: 3 :: Only
Classifier: Intended Audience :: Science/Research
Classifier: Operating System :: POSIX
Classifier: Operating System :: POSIX :: Linux
Classifier: Operating System :: Microsoft :: Windows
Classifier: Operating System :: Microsoft :: Windows :: Windows 7
Classifier: Operating System :: Microsoft :: Windows :: Windows 10
Classifier: Topic :: Scientific/Engineering
Classifier: Topic :: Education
Requires-Python: >=3.4
License-File: LICENCE.txt
License-File: AUTHORS.md
Requires-Dist: eccw (>=1.1.1)
Requires-Dist: matplotlib (>=3.1)
Requires-Dist: numpy (>=1.10)
Requires-Dist: pyqt5 (>=5.6)
Requires-Dist: xmltodict (>=0.10)
